csv2api/__init__.py
csv2api/app.py
csv2api/cli.py
csv2api-0.1.1.dist-info/LICENSE
csv2api-0.1.1.dist-info/METADATA
csv2api-0.1.1.dist-info/WHEEL
csv2api-0.1.1.dist-info/entry_points.txt
csv2api-0.1.1.dist-info/top_level.txt
csv2api-0.1.1.dist-info/RECORD
