Metadata-Version: 2.1
Name: csv2api
Version: 0.1.1
Summary: Turn any CSV into a REST API with one command.
Author-email: Mridul Sharma <sharma.mridul217@gmail.com>
Requires-Python: >=3.7
License-File: LICENSE
Requires-Dist: fastapi
Requires-Dist: uvicorn
Requires-Dist: pandas
Requires-Dist: typer[all]
